README.rst
setup.cfg
setup.py
cwstoolkit/Qiniu.py
cwstoolkit/__init__.py
cwstoolkit/dingding.py
cwstoolkit/mail.py
cwstoolkit/settings.py
cwstoolkit/sms.py
cwstoolkit/utilsBase.py
cwstoolkit/utilsDate.py
cwstoolkit/utilsLog.py
cwstoolkit.egg-info/PKG-INFO
cwstoolkit.egg-info/SOURCES.txt
cwstoolkit.egg-info/dependency_links.txt
cwstoolkit.egg-info/requires.txt
cwstoolkit.egg-info/top_level.txt