Metadata-Version: 1.0
Name: cwstoolkit
Version: 1.0.3
Summary: colinspace smart-devops toolkits
Home-page: https://github.com/opscolin/colinspace
Author: Colin
Author-email: colinspace@126.com
License: MIT
Keywords: colinspace,Colin,python,toolkits,colinws
Platform: Linux
Platform: Unix
Platform: Mac
